<?xml version="1.0" encoding="UTF-8"?>
<e57m xmlns:vc="http://www.w3.org/2007/XMLSchema-versioning"
 xmlns:xsi="http://www.w3.org/2001/XMLSchema-instance"
 xsi:noNamespaceSchemaLocation="2015_01_27_duraark_e57m_1_1.xsd">
    <E57root>
        <guid>{7E3C7C9C-EFCB-4F5A-9A6F-98A08F72FB1B}</guid>
        <version>1.0</version>
        <creation_datetime>2011-11-03T19:05:35</creation_datetime>
        <coordinate_metadata>undefined</coordinate_metadata>
        <scan_count>5</scan_count>
        <image_count>5</image_count>
        <scan_size>10</scan_size>
        <image_size>255</image_size>
    </E57root>
    <e57scan>
        <guid>{F0B3C105-325B-4FC9-9E01-3130153F9800}</guid>
        <name>parking000</name>
        <original_guids>{G1C4D216-436C-4FC9-9E01-4241264G0911}</original_guids>
        <description>Part1 Scan of 1st floor hallway.</description>
        <sensor_vendor>FARO Scanner Production GmbH</sensor_vendor>
        <sensor_model>FARO Focus 3D S 120</sensor_model>
        <sensor_serial_number>XXY0714889234T</sensor_serial_number>
        <sensor_hardware_version>3.001.124</sensor_hardware_version>
        <sensor_software_version>4.8.0.23502</sensor_software_version>
        <sensor_firmware_version>"iQLib" 5.0.6.30068</sensor_firmware_version>
        <temperature>18.4</temperature>
        <relative_humidity>23</relative_humidity>
        <atmospheric_pressure>101325</atmospheric_pressure>
        <acquisition_start>2011-11-02T13:45:21</acquisition_start>
        <acquisition_end>2011-11-02T14:34:32</acquisition_end>
        <pose>
            <rotation>
                <w>0.99996960774189081</w>
                <x>-0.0074585516927261801</x>
                <y>-0.0022701539983015365</y>
                <z>0</z>
            </rotation>
            <translation>
                <x>89.951072690000004</x>
                <y>1.8420018</y>
                <z>2e-008</z>
            </translation>
        </pose>
        <index_bounds>
            <row_minimum>0</row_minimum>
            <row_maximum>3470</row_maximum>
            <col_minimum>0</col_minimum>
            <col_maximum>8213</col_maximum>
            <return_minimum>0</return_minimum>
            <return_maximum>0</return_maximum>
        </index_bounds>
        <cartesian_bounds>
            <x_minimum>-68.432470999999993</x_minimum>
            <x_maximum>57.134830999999998</x_maximum>
            <y_minimum>-59.897230999999998</y_minimum>
            <y_maximum>70.512130999999997</y_maximum>
            <z_minimum>-2.0202709999999997</z_minimum>
            <z_maximum>3.779801</z_maximum>
        </cartesian_bounds>
        <sphericalbounds>
            <range_minimum>1.6562939999999999</range_minimum>
            <range_maximum>90.929899999999989</range_maximum>
            <elevation_minimum>-1.0909121353667537</elevation_minimum>
            <elevation_maximum>1.5701933463079427</elevation_maximum>
            <azimuth_minimum>0</azimuth_minimum>
            <azimuth_maximum>-6.4112263142845904e-007</azimuth_maximum>
        </sphericalbounds>
        <intensity_limits>
            <intensity_minimum>0</intensity_minimum>
            <intensity_maximum>1</intensity_maximum>
        </intensity_limits>
        <color_limits>
            <color_red_minimum>0</color_red_minimum>
            <color_red_maximum>255</color_red_maximum>
            <color_green_minimum>0</color_green_minimum>
            <color_green_maximum>255</color_green_maximum>
            <color_blue_minimum>0</color_blue_minimum>
            <color_blue_maximum>255</color_blue_maximum>
        </color_limits>
        <pointSize>26602731</pointSize>
        <point_fields>
            <cartesian_fields>
                <cartesian_x_field>true</cartesian_x_field>
                <cartesian_y_field>true</cartesian_y_field>
                <cartesian_z_field>true</cartesian_z_field>
                <cartesian_invalid_state_field>false</cartesian_invalid_state_field>
            </cartesian_fields>
            <spherical_fields>
                <spherical_range_field>true</spherical_range_field>
                <spherical_elevation_field>true</spherical_elevation_field>
                <spherical_azimuth_field>true</spherical_azimuth_field>
                <spherical_invalid_state_field>false</spherical_invalid_state_field>
            </spherical_fields>
            <point_range>
                <point_range_minimum>268.435454999999999</point_range_minimum>
                <point_range_maximum>-268.43545499999999</point_range_maximum>
                <point_range_scaled_integer>9.9999999999999995e-007</point_range_scaled_integer>
            </point_range>
            <angles>
                <angle_minimum>0</angle_minimum>
                <angle_maximum>0</angle_maximum>
                <angle_scaled_integer>0</angle_scaled_integer>
            </angles>
            <index_fields>
                <row_index_field>true</row_index_field>
                <row_index_maximum>4294967295</row_index_maximum>
                <column_index_field>true</column_index_field>
                <column_index_maximum>4294967295</column_index_maximum>
                <return_index_field>false</return_index_field>
                <return_count_field>false</return_count_field>
                <return_maximum>0</return_maximum>
            </index_fields>
            <time_fields>
                <time_stamp_field>true</time_stamp_field>
                <is_Time_Stamp_invalid>true</is_Time_Stamp_invalid>
                <time_Maximum>0</time_Maximum>
            </time_fields>
            <intensity_color_fields>
                <intensity_field>true</intensity_field>
                <is_intensity_invalid_field>false</is_intensity_invalid_field>
                <intensity_scaled_integer>0.00048851978505129456</intensity_scaled_integer>
                <color_red_field>true</color_red_field>
                <color_green_field>true</color_green_field>
                <color_blue_field>true</color_blue_field>
                <is_color_invalid_field>false</is_color_invalid_field>
            </intensity_color_fields>
        </point_fields>
    </e57scan>
    <e57image>
        <name>parking000image</name>
        <guid>{76BD148C-D22A-4FE3-8CB2-0FB01F96698B}</guid>
        <representation>spherical</representation>
        <description>This is a jpeg image taken at the same time as the 3D capture.</description>
        <acquisition_datetime>2011-11-02T14:34:32</acquisition_datetime>
        <associated_data3D_guid>{F0B3C105-325B-4FC9-9E01-3130153F9800}</associated_data3D_guid>
        <sensor_vendor>FARO Scanner Production GmbH</sensor_vendor>
        <sensor_model>FARO Focus 3D S210</sensor_model>
        <sensor_serial_number>XXXY0714889234T</sensor_serial_number>
        <pose>
            <rotation>
                <w>0.70283815264201144</w>
                <x>0.077691052038131911</x>
                <y>0.088163333920523737</y>
                <z>0.070127669443617587</z>
            </rotation>
            <translation>
                <x>89.951072690000004</x>
                <y>1.8420018</y>
                <z>2e-008</z>
            </translation>
        </pose>
        <visual_ref_representation>
            <jpeg_image_size>0</jpeg_image_size>
            <png_image_size>23551883</png_image_size>
            <image_mask_size>0</image_mask_size>
            <image_width>8187</image_width>
            <image_height>3471</image_height>
        </visual_ref_representation>
        <spherical_representation>
            <jpeg_image_size>0</jpeg_image_size>
            <png_image_size>23551883</png_image_size>
            <image_mask_size>0</image_mask_size>
            <image_width>8187</image_width>
            <image_height>3471</image_height>
            <pixel_width>0.0076745772193576565</pixel_width>
            <pixel_height>0.007666681778157584</pixel_height>
        </spherical_representation>
        <pinhole_representation>
            <jpeg_image_size>23551883</jpeg_image_size>
            <png_image_size>0</png_image_size>
            <image_mask_size>0</image_mask_size>
            <image_width>8187</image_width>
            <image_height>3471</image_height>
            <focal_length>1.5</focal_length>
            <pixel_width>0.0076745772193576565</pixel_width>
            <pixel_height>0.007666681778157584</pixel_height>
            <principal_point_x>4576</principal_point_x>
            <principal_point_y>1735</principal_point_y>
        </pinhole_representation>
        <cylindrical_representation>
            <jpeg_image_size>23551883</jpeg_image_size>
            <png_image_size>0</png_image_size>
            <image_mask_size>0</image_mask_size>
            <image_width>8187</image_width>
            <image_height>3471</image_height>
            <pixel_width>1.5</pixel_width>
            <pixel_height>0.0076745772193576565</pixel_height>
            <radius>0.007666681778157584</radius>
            <principal_point_y>1.25</principal_point_y>
        </cylindrical_representation>
    </e57image>
</e57m>
